mkctest1/__init__.py
mkctest1/lib2.py
mkctest1-0.5.0.dist-info/METADATA
mkctest1-0.5.0.dist-info/WHEEL
mkctest1-0.5.0.dist-info/top_level.txt
mkctest1-0.5.0.dist-info/RECORD
