Metadata-Version: 2.1
Name: mkctest1
Version: 0.5.0
Summary: Taiwan No. 1
Home-page: http://github.com/storborg/funniest
Author: Michael Chen
Author-email: flyingcircus@example.com
License: MIT
Platform: UNKNOWN
